{
  "--theme-primary": "#1e237e",
  "--theme-secondary": "#003ea9",
  "--theme-tertiary": "#565656",
  "--theme-background": "#f2f4f8",
  "--theme-action-primary": "#003ea9",
  "--theme-action-primary--hover": "#1869d6",
  "--theme-action-primary--disabled": "#b7c9e7",
  "--theme-action-primary--inactive": "#b7c9e7",
  "--theme-action-primary--selected": "#003ea9",
  "--theme-action-secondary": "#fff",
  "--theme-action-secondary--hover": "#57587d",
  "--theme-action-secondary--disabled": "#fff",
  "--theme-action-secondary--selected": "#57587d",
  "--theme-action-tertiary": "#fff",
  "--theme-action-tertiary--hover": "#fff",
  "--theme-action-tertiary--disabled": "#fff",
  "--theme-action-tertiary--selected": "#fff",
  "--theme-action-toggle": "#212a58",
  "--theme-action-toggle--hover": "#57587d",
  "--theme-action-toggle--disabled": "#c2c0cb",
  "--theme-action-toggle--selected": "#6f7099",
  "--theme-action-fixed": "#f2f4f8",
  "--theme-action-favorite": "#00329e",
  "--theme-action-input--active": "#b7c9e7",
  "--theme-action-input--disabled": "#6f7083",
  "--theme-font": "OpenSans,sans-serif",
  "--theme-font-color": "#565656",
  "--theme-font-color-dark": "#363636",
  "--theme-font-color-info": "#57587d",
  "--theme-font-size": "14px",
  "--theme-font-weight--light": "300",
  "--theme-font-weight--regular": "500",
  "--theme-font-weight--bold": "700",
  "--theme-font-direction": "ltr",
  "--theme-line-height": "1.78571rem",
  "--theme-link-color": "var(--theme-primary, #1e237e)",
  "--theme-link-color--hover": "var(--theme-secondary, #003ea9)",
  "--theme-link-underline": "none",
  "--theme-link-underline--hover": "underline",
  "--theme-focus-outline-color": "#15195a",
  "--theme-notification-positive": "#038703",
  "--theme-notification-neutral": "#6f7083",
  "--theme-notification-warning": "#ff9800",
  "--theme-notification-negative": "#d60036",
  "--theme-notification-foreground-light": "#fff",
  "--theme-notification-foreground-dark": "#222",
  "--theme-grid-width-small": "540px",
  "--theme-grid-width-medium": "860px",
  "--theme-grid-width-large": "1180px",
  "--theme-grid-col-gutter": "20px",
  "--theme-grid-col-padding": "6px 10px",
  "--theme-navigation-background": "#15195a",
  "--theme-navigation-foreground": "#fff",
  "--theme-navigation-border": "#1e237e",
  "--theme-navigation-item-hover": "#8b8b8b",
  "--theme-progress-background": "#f7b600",
  "--theme-progress-foreground": "#0842a6",
  "--theme-button--radius": "0",
  "--theme-button--default-text": "#fff",
  "--theme-button--default-text--hover": "#fff",
  "--theme-button--default-text--disabled": "#fff",
  "--theme-button--default-text--selected": "#fff",
  "--theme-button--secondary-text": "#57587d",
  "--theme-button--secondary-text--hover": "#fff",
  "--theme-button--secondary-text--disabled": "#6f7083",
  "--theme-button--secondary-text--selected": "#fff",
  "--theme-button--secondary-border": "#57587d",
  "--theme-button-icon-text": "#212a58",
  "--theme-button-icon--tertiary-text--selected": "#6f7099",
  "--theme-button--tertiary-text": "#003ea9",
  "--theme-button--teritary-text--hover": "#1869d6",
  "--theme-button--tertiary-text--disabled": "#b7c9e7",
  "--theme-button--tertiary-text--selected": "#1869d6",
  "--theme-avatar-initials-background": "#57587d",
  "--theme-avatar-logo-background": "var(--theme-navigation-background, #15195a)",
  "--theme-input-background": "#fff",
  "--theme-listbox-background": "#fff",
  "--theme-listbox-background--hover": "#f2f4f8",
  "--theme-listbox-border": "#e8f0fb",
  "--theme-sidepanel-background": "#fff",
  "--theme-sidepanel-border": "#9b9b9b",
  "--theme-slider-background": "#e0e1e5",
  "--theme-slider-node-background": "#fff",
  "--theme-slider-node-background--hover": "#003ea9",
  "--theme-slider-node-border": "#57587d",
  "--theme-status--not-started": "#6f7083",
  "--theme-status--completed": "#1869d6",
  "--theme-status--approved": "#398c47",
  "--theme-status--in-progress-indicator": "#ccd8ee"
}